README.md
setup.py
2op_ai.egg-info/PKG-INFO
2op_ai.egg-info/SOURCES.txt
2op_ai.egg-info/dependency_links.txt
2op_ai.egg-info/requires.txt
2op_ai.egg-info/top_level.txt
src/__init__.py
src/finetuning.py
src/main.py
src/processing.py