Metadata-Version: 2.1
Name: 2op-ai
Version: 0.1
Summary: A package for fine-tuning and utilizing the 2op_ai model
Home-page: https://github.com/sscla1/2op_ai
Author: Your Name
Author-email: sscla-ops@outlook.com
Keywords: machine-learning transformers fine-tuning ai
Classifier: Development Status :: 3 - Alpha
Classifier: Intended Audience :: Developers
Classifier: License :: OSI Approved :: MIT License
Classifier: Programming Language :: Python :: 3
Classifier: Programming Language :: Python :: 3.6
Classifier: Programming Language :: Python :: 3.7
Classifier: Programming Language :: Python :: 3.8
Classifier: Programming Language :: Python :: 3.9
